config.example.yaml
src/__init__.py
src/__main__.py
src/analyzer/__init__.py
src/analyzer/analyzer.py
src/analyzer/cache.py
src/analyzer/cli.py
src/analyzer/compatibility.py
src/analyzer/constraints.py
src/analyzer/peer_constraints.py
src/analyzer/python_constraint.py
src/analyzer/reporter.py
src/analyzer/resolver.py
src/analyzer/risk.py
src/analyzer/updater.py
src/config/__init__.py
src/config/config_loader.py
src/config/models.py
src/core/__init__.py
src/core/models.py
src/core/pypi_client.py
src/py.typed
src/utils/__init__.py
src/utils/prompt.py
depchk-0.9.5.dist-info/METADATA
depchk-0.9.5.dist-info/WHEEL
depchk-0.9.5.dist-info/entry_points.txt
depchk-0.9.5.dist-info/licenses/LICENSE
depchk-0.9.5.dist-info/RECORD
