Metadata-Version: 2.4
Name: depchk
Version: 0.9.5
Summary: Dependency version checker that analyzes pyproject.toml files and get upgrade recommendations
License: MIT
License-File: LICENSE
Keywords: python,dependencies,pypi,poetry,dependency-management,devtools,version-checker,upgrade-checker
Author: Robin Schulz
Author-email: bulletinmybeard@gmail.com
Requires-Python: >=3.12,<4.0
Classifier: Development Status :: 4 - Beta
Classifier: Environment :: Console
Classifier: Intended Audience :: Developers
Classifier: License :: OSI Approved :: MIT License
Classifier: Operating System :: MacOS
Classifier: Operating System :: POSIX :: Linux
Classifier: Programming Language :: Python :: 3
Classifier: Programming Language :: Python :: 3.12
Classifier: Programming Language :: Python :: 3.13
Classifier: Programming Language :: Python :: 3.14
Classifier: Topic :: Software Development :: Libraries :: Python Modules
Classifier: Topic :: Software Development :: Quality Assurance
Classifier: Topic :: System :: Software Distribution
Classifier: Typing :: Typed
Requires-Dist: aiohttp (>=3.13.2,<4.0.0)
Requires-Dist: chalkbox (>=2.3.5,<3.0.0)
Requires-Dist: packaging (>=21.0)
Requires-Dist: pydantic (>=2.12.5,<3.0.0) ; python_full_version >= "3.12.0" and python_version < "3.15"
Requires-Dist: pyyaml (>=6.0.3,<7.0.0)
Requires-Dist: tomlkit (>=0.13.3,<0.14.0)
Project-URL: Documentation, https://github.com/bulletinmybeard/depchk
Project-URL: Homepage, https://github.com/bulletinmybeard/depchk
Project-URL: Repository, https://github.com/bulletinmybeard/depchk
